[{"id":5727,"name":"acorn","details":null,"source":"Shaking a hardwood tree (Fall)","diy":false,"buy":null,"sell":200,"colors":[],"variants":[[{"id":5727,"filename":"https://storage.googleapis.com/acdb/other/DIYAcorn.png","colors":[]}]],"recipe":null,"tag":"NA"},{"id":2213,"name":"apple","details":null,"source":"Apple tree","diy":false,"buy":400,"sell":500,"colors":[],"variants":[[{"id":2213,"filename":"https://storage.googleapis.com/acdb/other/Apple.png","colors":[]}]],"recipe":null,"tag":"NA"},{"id":3360,"name":"apple tree","details":null,"source":"Planting an apple","diy":false,"buy":null,"sell":300,"colors":[],"variants":[[{"id":3360,"filename":"https://storage.googleapis.com/acdb/other/PltApple4.png","colors":[]}]],"recipe":null,"tag":"Plants"},{"id":5986,"name":"Aquarius fragment","details":null,"source":"Wishing on shooting stars (January 20 - February 18)","diy":false,"buy":null,"sell":500,"colors":[],"variants":[[{"id":5986,"filename":"https://storage.googleapis.com/acdb/other/StarpieceAquarius.png","colors":[]}]],"recipe":null,"tag":"NA"},{"id":5988,"name":"Aries fragment","details":null,"source":"Wishing on shooting stars (March 21 - April 19)","diy":false,"buy":null,"sell":500,"colors":[],"variants":[[{"id":5988,"filename":"https://storage.googleapis.com/acdb/other/StarpieceAries.png","colors":[]}]],"recipe":null,"tag":"NA"},{"id":2501,"name":"bamboo piece","details":null,"source":"Chopping a bamboo tree","diy":false,"buy":null,"sell":80,"colors":[],"variants":[[{"id":2501,"filename":"https://storage.googleapis.com/acdb/other/DIYBamboo.png","colors":[]}]],"recipe":null,"tag":"NA"},{"id":2295,"name":"bamboo shoot","details":null,"source":"Dig spot near a bamboo tree","diy":false,"buy":null,"sell":250,"colors":[],"variants":[[{"id":2295,"filename":"https://storage.googleapis.com/acdb/other/BambooShoot.png","colors":[]}]],"recipe":null,"tag":"NA"},{"id":2815,"name":"bamboo tree","details":null,"source":"Planting a bamboo shoot","diy":false,"buy":null,"sell":1500,"colors":[],"variants":[[{"id":2815,"filename":"https://storage.googleapis.com/acdb/other/PltBamboo4.png","colors":[]}]],"recipe":null,"tag":"Plants"},{"id":7731,"name":"Bell bag","details":null,"source":"Glowing dig spot","diy":false,"buy":null,"sell":null,"colors":[],"variants":[[{"id":7731,"filename":"https://storage.googleapis.com/acdb/other/PhotoStudioBellBag.png","colors":[]}]],"recipe":null,"tag":"NA"},{"id":2779,"name":"birthday cupcake","details":null,"source":"Birthday","diy":false,"buy":null,"sell":200,"colors":[],"variants":[[{"id":2779,"filename":"https://storage.googleapis.com/acdb/other/BirthdayCupcake.png","colors":[]}]],"recipe":null,"tag":"Seasonal Decor"},{"id":2875,"name":"black cosmos","details":null,"source":"Picking flowers","diy":false,"buy":null,"sell":240,"colors":[],"variants":[[{"id":2875,"filename":"https://storage.googleapis.com/acdb/other/FlwCosmosBlack.png","colors":[]}]],"recipe":null,"tag":"Plants"},{"id":2999,"name":"black lilies","details":null,"source":"Picking flowers","diy":false,"buy":null,"sell":80,"colors":[],"variants":[[{"id":2999,"filename":"https://storage.googleapis.com/acdb/other/FlwYuriBlack.png","colors":[]}]],"recipe":null,"tag":"Plants"},{"id":2955,"name":"black roses","details":null,"source":"Picking flowers","diy":false,"buy":null,"sell":240,"colors":[],"variants":[[{"id":2955,"filename":"https://storage.googleapis.com/acdb/other/FlwRoseBlack.png","colors":[]}]],"recipe":null,"tag":"Plants"},{"id":2903,"name":"black tulips","details":null,"source":"Picking flowers","diy":false,"buy":null,"sell":80,"colors":[],"variants":[[{"id":2903,"filename":"https://storage.googleapis.com/acdb/other/FlwTulipBlack.png","colors":[]}]],"recipe":null,"tag":"Plants"},{"id":7698,"name":"black wrapping paper","details":null,"source":"Nook's Cranny","diy":false,"buy":160,"sell":40,"colors":[],"variants":[[{"id":7698,"filename":"https://storage.googleapis.com/acdb/other/WPaperBlack.png","colors":[]}]],"recipe":null,"tag":"NA"},{"id":3834,"name":"black-cosmos plant","details":null,"source":"Red/red cosmos","diy":false,"buy":null,"sell":240,"colors":[],"variants":[[{"id":3834,"filename":"https://storage.googleapis.com/acdb/other/PltCosmosBlack3.png","colors":[]}]],"recipe":null,"tag":"Plants"},{"id":3896,"name":"black-lily plant","details":null,"source":"Red/red lilies","diy":false,"buy":null,"sell":80,"colors":[],"variants":[[{"id":3896,"filename":"https://storage.googleapis.com/acdb/other/PltYuriBlack3.png","colors":[]}]],"recipe":null,"tag":"Plants"},{"id":3874,"name":"black-rose plant","details":null,"source":"Red/red roses","diy":false,"buy":null,"sell":240,"colors":[],"variants":[[{"id":3874,"filename":"https://storage.googleapis.com/acdb/other/PltRoseBlack3.png","colors":[]}]],"recipe":null,"tag":"Plants"},{"id":3848,"name":"black-tulip plant","details":null,"source":"Red/red tulips","diy":false,"buy":null,"sell":80,"colors":[],"variants":[[{"id":3848,"filename":"https://storage.googleapis.com/acdb/other/PltTulipBlack3.png","colors":[]}]],"recipe":null,"tag":"Plants"},{"id":2755,"name":"Blathers's tent marker","details":null,"source":"Tom Nook","diy":false,"buy":null,"sell":null,"colors":[],"variants":[[{"id":2755,"filename":"https://storage.googleapis.com/acdb/other/MuseumTent.png","colors":[]}]],"recipe":null,"tag":"NA"},{"id":3748,"name":"blue hyacinths","details":null,"source":"Picking flowers","diy":false,"buy":null,"sell":80,"colors":[],"variants":[[{"id":3748,"filename":"https://storage.googleapis.com/acdb/other/FlwHyacinthBlue.png","colors":[]}]],"recipe":null,"tag":"Plants"},{"id":5731,"name":"blue ornament","details":null,"source":"Shaking a cedar tree (Festive Season)","diy":false,"buy":null,"sell":50,"colors":[],"variants":[[{"id":5731,"filename":"https://storage.googleapis.com/acdb/other/DIYOrnamentBlue.png","colors":[]}]],"recipe":null,"tag":"NA"},{"id":2927,"name":"blue pansies","details":null,"source":"Picking flowers","diy":false,"buy":null,"sell":80,"colors":[],"variants":[[{"id":2927,"filename":"https://storage.googleapis.com/acdb/other/FlwPansyBlue.png","colors":[]}]],"recipe":null,"tag":"Plants"},{"id":2959,"name":"blue roses","details":null,"source":"Picking flowers","diy":false,"buy":null,"sell":1000,"colors":[],"variants":[[{"id":2959,"filename":"https://storage.googleapis.com/acdb/other/FlwRoseBlue.png","colors":[]}]],"recipe":null,"tag":"Plants"},{"id":3717,"name":"blue windflowers","details":null,"source":"Picking flowers","diy":false,"buy":null,"sell":80,"colors":[],"variants":[[{"id":3717,"filename":"https://storage.googleapis.com/acdb/other/FlwAnemonesBlue.png","colors":[]}]],"recipe":null,"tag":"Plants"},{"id":7692,"name":"blue wrapping paper","details":null,"source":"Nook's Cranny","diy":false,"buy":160,"sell":40,"colors":[],"variants":[[{"id":7692,"filename":"https://storage.googleapis.com/acdb/other/WPaperBlue.png","colors":[]}]],"recipe":null,"tag":"NA"},{"id":3920,"name":"blue-hyacinth plant","details":null,"source":"White/white hyacinths","diy":false,"buy":null,"sell":80,"colors":[],"variants":[[{"id":3920,"filename":"https://storage.googleapis.com/acdb/other/PltHyacinthBlue3.png","colors":[]}]],"recipe":null,"tag":"Plants"},{"id":3860,"name":"blue-pansy plant","details":null,"source":"White/white pansies","diy":false,"buy":null,"sell":80,"colors":[],"variants":[[{"id":3860,"filename":"https://storage.googleapis.com/acdb/other/PltPansyBlue3.png","colors":[]}]],"recipe":null,"tag":"Plants"},{"id":3876,"name":"blue-rose plant","details":null,"source":"Orange/orange roses","diy":false,"buy":null,"sell":1000,"colors":[],"variants":[[{"id":3876,"filename":"https://storage.googleapis.com/acdb/other/PltRoseBlue3.png","colors":[]}]],"recipe":null,"tag":"Plants"},{"id":3902,"name":"blue-windflower plant","details":null,"source":"White/white windflowers\nOrange/white windflowers","diy":false,"buy":null,"sell":80,"colors":[],"variants":[[{"id":3902,"filename":"https://storage.googleapis.com/acdb/other/PltAnemonesBlue3.png","colors":[]}]],"recipe":null,"tag":"Plants"},{"id":3469,"name":"boot","details":"Medium shadow","source":"Fishing","diy":false,"buy":40,"sell":10,"colors":[],"variants":[[{"id":3469,"filename":"https://storage.googleapis.com/acdb/other/TrashBoot.png","colors":[]}]],"recipe":null,"tag":"NA"},{"id":7211,"name":"bridge construction kit","details":null,"source":"Tom Nook","diy":false,"buy":null,"sell":null,"colors":[],"variants":[[{"id":7211,"filename":"https://storage.googleapis.com/acdb/other/BridgeLogReserveKit.png","colors":[]}]],"recipe":null,"tag":"Outdoors Decor"},{"id":4310,"name":"bridge marker kit","details":null,"source":"Tom Nook","diy":false,"buy":null,"sell":null,"colors":[],"variants":[[{"id":4310,"filename":"https://storage.googleapis.com/acdb/other/BridgeReserveKit.png","colors":[]}]],"recipe":null,"tag":"NA"},{"id":7696,"name":"brown wrapping paper","details":null,"source":"Nook's Cranny","diy":false,"buy":160,"sell":40,"colors":[],"variants":[[{"id":7696,"filename":"https://storage.googleapis.com/acdb/other/WPaperBrown.png","colors":[]}]],"recipe":null,"tag":"NA"},{"id":5166,"name":"campsite construction kit","details":null,"source":"Tom Nook","diy":false,"buy":null,"sell":null,"colors":[],"variants":[[{"id":5166,"filename":"https://storage.googleapis.com/acdb/other/CampsiteReserveKit.png","colors":[]}]],"recipe":null,"tag":"NA"},{"id":6841,"name":"campsite moving kit","details":null,"source":"Tom Nook","diy":false,"buy":null,"sell":null,"colors":[],"variants":[[{"id":6841,"filename":"https://storage.googleapis.com/acdb/other/MovingKitCampsite.png","colors":[]}]],"recipe":null,"tag":"NA"},{"id":5991,"name":"Cancer fragment","details":null,"source":"Wishing on shooting stars (June 21 - July 22)","diy":false,"buy":null,"sell":500,"colors":[],"variants":[[{"id":5991,"filename":"https://storage.googleapis.com/acdb/other/StarpieceCancer.png","colors":[]}]],"recipe":null,"tag":"NA"},{"id":5985,"name":"Capricorn fragment","details":null,"source":"Wishing on shooting stars (Dec 22 - Jan 19)","diy":false,"buy":null,"sell":500,"colors":[],"variants":[[{"id":5985,"filename":"https://storage.googleapis.com/acdb/other/StarpieceCapricornus.png","colors":[]}]],"recipe":null,"tag":"NA"},{"id":2800,"name":"cedar sapling","details":null,"source":"Nook's Cranny","diy":false,"buy":640,"sell":160,"colors":[],"variants":[[{"id":2800,"filename":"https://storage.googleapis.com/acdb/other/SeedCedar.png","colors":[]}]],"recipe":null,"tag":"Plants"},{"id":2805,"name":"cedar tree","details":null,"source":"Planting a cedar start","diy":false,"buy":null,"sell":240,"colors":[],"variants":[[{"id":2805,"filename":"https://storage.googleapis.com/acdb/other/PltCedar4.png","colors":[]}]],"recipe":null,"tag":"Plants"},{"id":7686,"name":"chartreuse wrapping paper","details":null,"source":"Nook's Cranny","diy":false,"buy":160,"sell":40,"colors":[],"variants":[[{"id":7686,"filename":"https://storage.googleapis.com/acdb/other/WPaperLightGreen.png","colors":[]}]],"recipe":null,"tag":"NA"},{"id":2287,"name":"cherry","details":null,"source":"Cherry tree","diy":false,"buy":400,"sell":500,"colors":[],"variants":[[{"id":2287,"filename":"https://storage.googleapis.com/acdb/other/Cherry.png","colors":[]}]],"recipe":null,"tag":"NA"},{"id":3381,"name":"cherry tree","details":null,"source":"Planting a cherry","diy":false,"buy":null,"sell":300,"colors":[],"variants":[[{"id":3381,"filename":"https://storage.googleapis.com/acdb/other/PltCherry4.png","colors":[]}]],"recipe":null,"tag":"Plants"},{"id":5859,"name":"cherry-blossom petal","details":null,"source":"Catching with a net (Cherry-Blossom Season)","diy":false,"buy":null,"sell":null,"colors":[],"variants":[[{"id":5859,"filename":"https://storage.googleapis.com/acdb/other/Sakurapetal.png","colors":[]}]],"recipe":null,"tag":"NA"},{"id":3090,"name":"clay","details":null,"source":"Hitting a rock","diy":false,"buy":null,"sell":100,"colors":[],"variants":[[{"id":3090,"filename":"https://storage.googleapis.com/acdb/other/DIYClay.png","colors":[]}]],"recipe":null,"tag":"NA"},{"id":2624,"name":"clump of weeds","details":null,"source":"On ground","diy":false,"buy":null,"sell":10,"colors":[],"variants":[[{"id":2624,"filename":"https://storage.googleapis.com/acdb/other/PltWeed.png","colors":[]}]],"recipe":null,"tag":"Plants"},{"id":2288,"name":"coconut","details":null,"source":"Coconut tree","diy":false,"buy":null,"sell":250,"colors":[],"variants":[[{"id":2288,"filename":"https://storage.googleapis.com/acdb/other/Coconut.png","colors":[]}]],"recipe":null,"tag":"NA"},{"id":2810,"name":"coconut tree","details":null,"source":"Planting a coconut","diy":false,"buy":null,"sell":500,"colors":[],"variants":[[{"id":2810,"filename":"https://storage.googleapis.com/acdb/other/PltPalm4.png","colors":[]}]],"recipe":null,"tag":"Plants"},{"id":7730,"name":"coin","details":null,"source":"Shaking a tree","diy":false,"buy":null,"sell":0,"colors":[],"variants":[[{"id":7730,"filename":"https://storage.googleapis.com/acdb/other/PhotoStudioBell.png","colors":[]}]],"recipe":null,"tag":"NA"},{"id":2381,"name":"communicator part","details":null,"source":"Clam dig spot while on a quest for Gulliver","diy":false,"buy":null,"sell":20,"colors":[],"variants":[[{"id":2381,"filename":"https://storage.googleapis.com/acdb/other/JohnnyQuest1.png","colors":[]}]],"recipe":null,"tag":"NA"},{"id":1376,"name":"conch","details":null,"source":"Beach","diy":false,"buy":null,"sell":700,"colors":[],"variants":[[{"id":1376,"filename":"https://storage.googleapis.com/acdb/other/ShellDriftHora.png","colors":[]}]],"recipe":null,"tag":"NA"},{"id":1380,"name":"coral","details":null,"source":"Beach","diy":false,"buy":null,"sell":500,"colors":[],"variants":[[{"id":1380,"filename":"https://storage.googleapis.com/acdb/other/ShellDriftSango.png","colors":[]}]],"recipe":null,"tag":"NA"},{"id":1382,"name":"cowrie","details":null,"source":"Beach","diy":false,"buy":null,"sell":60,"colors":[],"variants":[[{"id":1382,"filename":"https://storage.googleapis.com/acdb/other/ShellDriftTakara.png","colors":[]}]],"recipe":null,"tag":"NA"},{"id":2513,"name":"customization kit","details":null,"source":"Nook's Cranny","diy":false,"buy":600,"sell":150,"colors":[],"variants":[[{"id":2513,"filename":"https://storage.googleapis.com/acdb/other/RemakeKit.png","colors":[]}]],"recipe":null,"tag":"Supplies"},{"id":4645,"name":"delivery","details":null,"source":"Delivering item for a villager","diy":false,"buy":null,"sell":222,"colors":[],"variants":[[{"id":4645,"filename":"https://storage.googleapis.com/acdb/other/DummyCardboard.png","colors":[]}]],"recipe":null,"tag":"NA"},{"id":4245,"name":"delivery box","details":null,"source":"Nook Shopping","diy":false,"buy":null,"sell":null,"colors":[],"variants":[[{"id":4245,"filename":"https://storage.googleapis.com/acdb/other/QuestWrappingBox.png","colors":[]}]],"recipe":null,"tag":"NA"},{"id":5603,"name":"DIY for Beginners","details":null,"source":"Nook's Cranny","diy":false,"buy":480,"sell":null,"colors":[],"variants":[[{"id":5603,"filename":"https://storage.googleapis.com/acdb/other/DIYbook1.png","colors":[]}]],"recipe":null,"tag":"NA"},{"id":12509,"name":"earth egg","details":null,"source":"Dig spot (Bunny Day)","diy":false,"buy":null,"sell":200,"colors":[],"variants":[[{"id":12509,"filename":"https://storage.googleapis.com/acdb/other/EggGround.png","colors":[]}]],"recipe":null,"tag":"NA"},{"id":12544,"name":"egg message bottle","details":null,"source":"Beach (Bunny Day)","diy":false,"buy":null,"sell":null,"colors":[],"variants":[[{"id":12544,"filename":"https://storage.googleapis.com/acdb/other/MessageBottleEgg.png","colors":[]}]],"recipe":null,"tag":"NA"},{"id":3276,"name":"elegant mushroom","details":null,"source":"On ground (Mushroom Season)","diy":false,"buy":null,"sell":10000,"colors":[],"variants":[[{"id":3276,"filename":"https://storage.googleapis.com/acdb/other/MushSplendid.png","colors":[]}]],"recipe":null,"tag":"NA"},{"id":3466,"name":"empty can","details":"Small shadow","source":"Fishing","diy":false,"buy":null,"sell":10,"colors":[],"variants":[[{"id":3466,"filename":"https://storage.googleapis.com/acdb/other/TrashCan.png","colors":[]}]],"recipe":null,"tag":"NA"},{"id":4549,"name":"fish bait","details":null,"source":"Crafting","diy":false,"buy":null,"sell":200,"colors":[],"variants":[[{"id":4549,"filename":"https://storage.googleapis.com/acdb/other/FishBait.png","colors":[]}]],"recipe":null,"tag":"NA"},{"id":3279,"name":"flat mushroom","details":null,"source":"On ground (Mushroom Season)","diy":false,"buy":null,"sell":200,"colors":[],"variants":[[{"id":3279,"filename":"https://storage.googleapis.com/acdb/other/MushFlat.png","colors":[]}]],"recipe":null,"tag":"NA"},{"id":12294,"name":"Flimsy Axe Recipe","details":"Available after unlocking the axe in the story","source":"Nook's Cranny","diy":false,"buy":280,"sell":200,"colors":[],"variants":[[{"id":12294,"filename":"https://storage.googleapis.com/acdb/other/DIYRecipeAxeWood.png","colors":[]}]],"recipe":null,"tag":"NA"},{"id":9047,"name":"Flimsy Shovel Recipe","details":"Available after unlocking the shovel in the story","source":"Nook's Cranny","diy":false,"buy":280,"sell":200,"colors":[],"variants":[[{"id":9047,"filename":"https://storage.googleapis.com/acdb/other/DIYRecipeScoopWood.png","colors":[]}]],"recipe":null,"tag":"NA"},{"id":9048,"name":"Flimsy Watering Can Recipe","details":null,"source":"Nook's Cranny","diy":false,"buy":280,"sell":200,"colors":[],"variants":[[{"id":9048,"filename":"https://storage.googleapis.com/acdb/other/DIYRecipeWateringWood.png","colors":[]}]],"recipe":null,"tag":"NA"},{"id":2579,"name":"fossil","details":null,"source":"Dig spot","diy":false,"buy":null,"sell":100,"colors":[],"variants":[[{"id":2579,"filename":"https://storage.googleapis.com/acdb/other/Fossil.png","colors":[]}]],"recipe":null,"tag":"NA"},{"id":5990,"name":"Gemini fragment","details":null,"source":"Wishing on shooting stars (May 21 - June 20)","diy":false,"buy":null,"sell":500,"colors":[],"variants":[[{"id":5990,"filename":"https://storage.googleapis.com/acdb/other/StarpieceGemini.png","colors":[]}]],"recipe":null,"tag":"NA"},{"id":1381,"name":"giant clam","details":null,"source":"Beach","diy":false,"buy":null,"sell":900,"colors":[],"variants":[[{"id":1381,"filename":"https://storage.googleapis.com/acdb/other/ShellDriftSyako.png","colors":[]}]],"recipe":null,"tag":"NA"},{"id":2505,"name":"gold nugget","details":null,"source":"Hitting a rock","diy":false,"buy":null,"sell":10000,"colors":[],"variants":[[{"id":2505,"filename":"https://storage.googleapis.com/acdb/other/DIYGold.png","colors":[]}]],"recipe":null,"tag":"NA"},{"id":5732,"name":"gold ornament","details":null,"source":"Shaking a cedar tree (Festive Season)","diy":false,"buy":null,"sell":50,"colors":[],"variants":[[{"id":5732,"filename":"https://storage.googleapis.com/acdb/other/DIYOrnamentGold.png","colors":[]}]],"recipe":null,"tag":"NA"},{"id":2963,"name":"gold roses","details":null,"source":"Picking flowers","diy":false,"buy":null,"sell":1000,"colors":[],"variants":[[{"id":2963,"filename":"https://storage.googleapis.com/acdb/other/FlwRoseGold.png","colors":[]}]],"recipe":null,"tag":"Plants"},{"id":7695,"name":"gold wrapping paper","details":null,"source":"Nook's Cranny","diy":false,"buy":160,"sell":40,"colors":[],"variants":[[{"id":7695,"filename":"https://storage.googleapis.com/acdb/other/WPaperGold.png","colors":[]}]],"recipe":null,"tag":"NA"},{"id":3878,"name":"gold-rose plant","details":null,"source":"Black/black roses\nWater with gold watering can","diy":false,"buy":null,"sell":1000,"colors":[],"variants":[[{"id":3878,"filename":"https://storage.googleapis.com/acdb/other/PltRoseGold3.png","colors":[]}]],"recipe":null,"tag":"Plants"},{"id":7697,"name":"gray wrapping paper","details":null,"source":"Nook's Cranny","diy":false,"buy":160,"sell":40,"colors":[],"variants":[[{"id":7697,"filename":"https://storage.googleapis.com/acdb/other/WPaperGray.png","colors":[]}]],"recipe":null,"tag":"NA"},{"id":5175,"name":"green mums","details":null,"source":"Picking flowers","diy":false,"buy":null,"sell":240,"colors":[],"variants":[[{"id":5175,"filename":"https://storage.googleapis.com/acdb/other/FlwMumGreen.png","colors":[]}]],"recipe":null,"tag":"Plants"},{"id":7687,"name":"green wrapping paper","details":null,"source":"Nook's Cranny","diy":false,"buy":160,"sell":40,"colors":[],"variants":[[{"id":7687,"filename":"https://storage.googleapis.com/acdb/other/WPaperGreen.png","colors":[]}]],"recipe":null,"tag":"NA"},{"id":3934,"name":"green-mum plant","details":null,"source":"Purple/purple mums","diy":false,"buy":null,"sell":240,"colors":[],"variants":[[{"id":3934,"filename":"https://storage.googleapis.com/acdb/other/PltMumGreen3.png","colors":[]}]],"recipe":null,"tag":"Plants"},{"id":2769,"name":"hardwood","details":null,"source":"Chopping a tree","diy":false,"buy":null,"sell":60,"colors":[],"variants":[[{"id":2769,"filename":"https://storage.googleapis.com/acdb/other/DIYWoodHard.png","colors":[]}]],"recipe":null,"tag":"NA"},{"id":2799,"name":"hardwood tree","details":null,"source":"Planting a sapling","diy":false,"buy":null,"sell":240,"colors":[],"variants":[[{"id":2799,"filename":"https://storage.googleapis.com/acdb/other/PltOak4.png","colors":[]}]],"recipe":null,"tag":"Plants"},{"id":3349,"name":"housing kit","details":null,"source":"Tom Nook","diy":false,"buy":null,"sell":null,"colors":[],"variants":[[{"id":3349,"filename":"https://storage.googleapis.com/acdb/other/NnpcNewHousingkit.png","colors":[]}]],"recipe":null,"tag":"NA"},{"id":4311,"name":"incline marker kit","details":null,"source":"Tom Nook","diy":false,"buy":null,"sell":null,"colors":[],"variants":[[{"id":4311,"filename":"https://storage.googleapis.com/acdb/other/SlopeReserveKit.png","colors":[]}]],"recipe":null,"tag":"NA"},{"id":2511,"name":"iron nugget","details":null,"source":"Hitting a rock","diy":false,"buy":null,"sell":375,"colors":[],"variants":[[{"id":2511,"filename":"https://storage.googleapis.com/acdb/other/DIYIron.png","colors":[]}]],"recipe":null,"tag":"NA"},{"id":12327,"name":"Ladder Recipe","details":"Available after unlocking the ladder in the story","source":"Nook's Cranny","diy":false,"buy":500,"sell":200,"colors":[],"variants":[[{"id":12327,"filename":"https://storage.googleapis.com/acdb/other/DIYRecipeLadder.png","colors":[]}]],"recipe":null,"tag":"NA"},{"id":3540,"name":"large snowflake","details":null,"source":"Perfect Snowboy","diy":false,"buy":null,"sell":null,"colors":[],"variants":[[{"id":3540,"filename":"https://storage.googleapis.com/acdb/other/SnowCrystalLarge.png","colors":[]}]],"recipe":null,"tag":"NA"},{"id":5984,"name":"large star fragment","details":null,"source":"Wishing on shooting stars","diy":false,"buy":null,"sell":2500,"colors":[],"variants":[[{"id":5984,"filename":"https://storage.googleapis.com/acdb/other/StarpieceRare.png","colors":[]}]],"recipe":null,"tag":"NA"},{"id":12511,"name":"leaf egg","details":null,"source":"Shaking a hardwood tree (Bunny Day)","diy":false,"buy":null,"sell":200,"colors":[],"variants":[[{"id":12511,"filename":"https://storage.googleapis.com/acdb/other/EggLeaf.png","colors":[]}]],"recipe":null,"tag":"NA"},{"id":5992,"name":"Leo fragment","details":null,"source":"Wishing on shooting stars (July 23 - August 22)","diy":false,"buy":null,"sell":500,"colors":[],"variants":[[{"id":5992,"filename":"https://storage.googleapis.com/acdb/other/StarpieceLeo.png","colors":[]}]],"recipe":null,"tag":"NA"},{"id":5994,"name":"Libra fragment","details":null,"source":"Wishing on shooting stars (September 23 - October 22)","diy":false,"buy":null,"sell":500,"colors":[],"variants":[[{"id":5994,"filename":"https://storage.googleapis.com/acdb/other/StarpieceLibra.png","colors":[]}]],"recipe":null,"tag":"NA"},{"id":7689,"name":"light-blue wrapping paper","details":null,"source":"Nook's Cranny","diy":false,"buy":160,"sell":40,"colors":[],"variants":[[{"id":7689,"filename":"https://storage.googleapis.com/acdb/other/WPaperLightBlue.png","colors":[]}]],"recipe":null,"tag":"NA"},{"id":7651,"name":"lily-of-the-valley plant","details":null,"source":"5-star town status","diy":false,"buy":null,"sell":222,"colors":[],"variants":[[{"id":7651,"filename":"https://storage.googleapis.com/acdb/other/PltSuzuran2.png","colors":[]}]],"recipe":null,"tag":"Plants"},{"id":2374,"name":"lost item","details":null,"source":"On ground","diy":false,"buy":null,"sell":null,"colors":[],"variants":[[{"id":2374,"filename":"https://storage.googleapis.com/acdb/other/LostQuestBag.png","colors":[]},{"id":2375,"filename":"https://storage.googleapis.com/acdb/other/LostQuestBook.png","colors":[]},{"id":5426,"filename":"https://storage.googleapis.com/acdb/other/LostQuestNote.png","colors":[]}]],"recipe":null,"tag":"NA"},{"id":2375,"name":"lost item","details":null,"source":"On ground","diy":false,"buy":null,"sell":null,"colors":[],"variants":[[{"id":2374,"filename":"https://storage.googleapis.com/acdb/other/LostQuestBag.png","colors":[]},{"id":2375,"filename":"https://storage.googleapis.com/acdb/other/LostQuestBook.png","colors":[]},{"id":5426,"filename":"https://storage.googleapis.com/acdb/other/LostQuestNote.png","colors":[]}]],"recipe":null,"tag":"NA"},{"id":5426,"name":"lost item","details":null,"source":"On ground","diy":false,"buy":null,"sell":null,"colors":[],"variants":[[{"id":2374,"filename":"https://storage.googleapis.com/acdb/other/LostQuestBag.png","colors":[]},{"id":2375,"filename":"https://storage.googleapis.com/acdb/other/LostQuestBook.png","colors":[]},{"id":5426,"filename":"https://storage.googleapis.com/acdb/other/LostQuestNote.png","colors":[]}]],"recipe":null,"tag":"NA"},{"id":2567,"name":"manila clam","details":null,"source":"Clam dig spot","diy":false,"buy":null,"sell":100,"colors":[],"variants":[[{"id":2567,"filename":"https://storage.googleapis.com/acdb/other/FtrShellFishAsari.png","colors":[]}]],"recipe":null,"tag":"NA"},{"id":7374,"name":"maple leaf","details":null,"source":"Catching with a net (Fall)","diy":false,"buy":null,"sell":null,"colors":[],"variants":[[{"id":7374,"filename":"https://storage.googleapis.com/acdb/other/AutumnLeaf.png","colors":[]}]],"recipe":null,"tag":"NA"},{"id":2777,"name":"medicine","details":null,"source":"Nook's Cranny","diy":false,"buy":400,"sell":100,"colors":[],"variants":[[{"id":2777,"filename":"https://storage.googleapis.com/acdb/other/ItemMedicine.png","colors":[]}]],"recipe":null,"tag":"Hospital"},{"id":5793,"name":"message bottle","details":null,"source":"Beach","diy":false,"buy":null,"sell":null,"colors":[],"variants":[[{"id":5793,"filename":"https://storage.googleapis.com/acdb/other/MessageBottle.png","colors":[]}]],"recipe":null,"tag":"NA"},{"id":7688,"name":"mint wrapping paper","details":null,"source":"Nook's Cranny","diy":false,"buy":160,"sell":40,"colors":[],"variants":[[{"id":7688,"filename":"https://storage.googleapis.com/acdb/other/WPaperMint.png","colors":[]}]],"recipe":null,"tag":"NA"},{"id":4426,"name":"money tree","details":null,"source":"Burying bells in a glowing spot","diy":false,"buy":null,"sell":240,"colors":[],"variants":[[{"id":4426,"filename":"https://storage.googleapis.com/acdb/other/PltMoney4.png","colors":[]}]],"recipe":null,"tag":"Plants"},{"id":5358,"name":"moving kit","details":null,"source":"Tom Nook","diy":false,"buy":null,"sell":null,"colors":[],"variants":[[{"id":5358,"filename":"https://storage.googleapis.com/acdb/other/MovingKitPlayer.png","colors":[]}]],"recipe":null,"tag":"NA"},{"id":5361,"name":"museum moving kit","details":null,"source":"Tom Nook","diy":false,"buy":null,"sell":null,"colors":[],"variants":[[{"id":5361,"filename":"https://storage.googleapis.com/acdb/other/MovingKitMuseum.png","colors":[]}]],"recipe":null,"tag":"NA"},{"id":7691,"name":"navy wrapping paper","details":null,"source":"Nook's Cranny","diy":false,"buy":160,"sell":40,"colors":[],"variants":[[{"id":7691,"filename":"https://storage.googleapis.com/acdb/other/WPaperNavy.png","colors":[]}]],"recipe":null,"tag":"NA"},{"id":3470,"name":"old tire","details":"Large shadow","source":"Fishing","diy":false,"buy":null,"sell":10,"colors":[],"variants":[[{"id":3470,"filename":"https://storage.googleapis.com/acdb/other/TrashTire.png","colors":[]}]],"recipe":null,"tag":"NA"},{"id":2214,"name":"orange","details":null,"source":"Orange tree","diy":false,"buy":400,"sell":500,"colors":[],"variants":[[{"id":2214,"filename":"https://storage.googleapis.com/acdb/other/Orange.png","colors":[]}]],"recipe":null,"tag":"NA"},{"id":2871,"name":"orange cosmos","details":null,"source":"Picking flowers","diy":false,"buy":null,"sell":80,"colors":[],"variants":[[{"id":2871,"filename":"https://storage.googleapis.com/acdb/other/FlwCosmosOrange.png","colors":[]}]],"recipe":null,"tag":"Plants"},{"id":3741,"name":"orange hyacinths","details":null,"source":"Picking flowers","diy":false,"buy":null,"sell":80,"colors":[],"variants":[[{"id":3741,"filename":"https://storage.googleapis.com/acdb/other/FlwHyacinthOrange.png","colors":[]}]],"recipe":null,"tag":"Plants"},{"id":2995,"name":"orange lilies","details":null,"source":"Picking flowers","diy":false,"buy":null,"sell":80,"colors":[],"variants":[[{"id":2995,"filename":"https://storage.googleapis.com/acdb/other/FlwYuriOrange.png","colors":[]}]],"recipe":null,"tag":"Plants"},{"id":2919,"name":"orange pansies","details":null,"source":"Picking flowers","diy":false,"buy":null,"sell":80,"colors":[],"variants":[[{"id":2919,"filename":"https://storage.googleapis.com/acdb/other/FlwPansyRedYellow.png","colors":[]}]],"recipe":null,"tag":"Plants"},{"id":2947,"name":"orange roses","details":null,"source":"Picking flowers","diy":false,"buy":null,"sell":80,"colors":[],"variants":[[{"id":2947,"filename":"https://storage.googleapis.com/acdb/other/FlwRoseOrange.png","colors":[]}]],"recipe":null,"tag":"Plants"},{"id":3365,"name":"orange tree","details":null,"source":"Planting an orange","diy":false,"buy":null,"sell":300,"colors":[],"variants":[[{"id":3365,"filename":"https://storage.googleapis.com/acdb/other/PltOrange4.png","colors":[]}]],"recipe":null,"tag":"Plants"},{"id":2895,"name":"orange tulips","details":null,"source":"Picking flowers","diy":false,"buy":null,"sell":80,"colors":[],"variants":[[{"id":2895,"filename":"https://storage.googleapis.com/acdb/other/FlwTulipOrange.png","colors":[]}]],"recipe":null,"tag":"Plants"},{"id":3713,"name":"orange windflowers","details":null,"source":"Picking flowers","diy":false,"buy":null,"sell":40,"colors":[],"variants":[[{"id":3713,"filename":"https://storage.googleapis.com/acdb/other/FlwAnemonesOrange.png","colors":[]}]],"recipe":null,"tag":"Plants"},{"id":7685,"name":"orange wrapping paper","details":null,"source":"Nook's Cranny","diy":false,"buy":160,"sell":40,"colors":[],"variants":[[{"id":7685,"filename":"https://storage.googleapis.com/acdb/other/WPaperOrange.png","colors":[]}]],"recipe":null,"tag":"NA"},{"id":3832,"name":"orange-cosmos plant","details":null,"source":"Red/yellow cosmos","diy":false,"buy":null,"sell":80,"colors":[],"variants":[[{"id":3832,"filename":"https://storage.googleapis.com/acdb/other/PltCosmosOrange3.png","colors":[]}]],"recipe":null,"tag":"Plants"},{"id":3916,"name":"orange-hyacinth plant","details":null,"source":"Red/yellow hyacinths","diy":false,"buy":null,"sell":80,"colors":[],"variants":[[{"id":3916,"filename":"https://storage.googleapis.com/acdb/other/PltHyacinthOrange3.png","colors":[]}]],"recipe":null,"tag":"Plants"},{"id":3894,"name":"orange-lily plant","details":null,"source":"Red/yellow lilies","diy":false,"buy":null,"sell":80,"colors":[],"variants":[[{"id":3894,"filename":"https://storage.googleapis.com/acdb/other/PltYuriOrange3.png","colors":[]}]],"recipe":null,"tag":"Plants"},{"id":3856,"name":"orange-pansy plant","details":null,"source":"Red/yellow pansies","diy":false,"buy":null,"sell":80,"colors":[],"variants":[[{"id":3856,"filename":"https://storage.googleapis.com/acdb/other/PltPansyRedYellow3.png","colors":[]}]],"recipe":null,"tag":"Plants"},{"id":3870,"name":"orange-rose plant","details":null,"source":"Red/yellow roses","diy":false,"buy":null,"sell":80,"colors":[],"variants":[[{"id":3870,"filename":"https://storage.googleapis.com/acdb/other/PltRoseOrange3.png","colors":[]}]],"recipe":null,"tag":"Plants"},{"id":3844,"name":"orange-tulip plant","details":null,"source":"Red/yellow tulips","diy":false,"buy":null,"sell":80,"colors":[],"variants":[[{"id":3844,"filename":"https://storage.googleapis.com/acdb/other/PltTulipOrange3.png","colors":[]}]],"recipe":null,"tag":"Plants"},{"id":3714,"name":"orange-windflower bag","details":null,"source":"Nook's Cranny","diy":false,"buy":240,"sell":60,"colors":[],"variants":[[{"id":3714,"filename":"https://storage.googleapis.com/acdb/other/SeedAnemonesOrange.png","colors":[]}]],"recipe":null,"tag":"Plants"},{"id":3900,"name":"orange-windflower plant","details":null,"source":"Seed bag","diy":false,"buy":null,"sell":40,"colors":[],"variants":[[{"id":3900,"filename":"https://storage.googleapis.com/acdb/other/PltAnemonesOrange3.png","colors":[]}]],"recipe":null,"tag":"Plants"},{"id":2286,"name":"peach","details":null,"source":"Peach tree","diy":false,"buy":400,"sell":500,"colors":[],"variants":[[{"id":2286,"filename":"https://storage.googleapis.com/acdb/other/Peach.png","colors":[]}]],"recipe":null,"tag":"NA"},{"id":3375,"name":"peach tree","details":null,"source":"Planting a peach","diy":false,"buy":null,"sell":300,"colors":[],"variants":[[{"id":3375,"filename":"https://storage.googleapis.com/acdb/other/PltPeach4.png","colors":[]}]],"recipe":null,"tag":"Plants"},{"id":2285,"name":"pear","details":null,"source":"Pear tree","diy":false,"buy":400,"sell":500,"colors":[],"variants":[[{"id":2285,"filename":"https://storage.googleapis.com/acdb/other/Pear.png","colors":[]}]],"recipe":null,"tag":"NA"},{"id":3370,"name":"pear tree","details":null,"source":"Planting a pear","diy":false,"buy":null,"sell":300,"colors":[],"variants":[[{"id":3370,"filename":"https://storage.googleapis.com/acdb/other/PltPear4.png","colors":[]}]],"recipe":null,"tag":"Plants"},{"id":5728,"name":"pine cone","details":null,"source":"Shaking a cedar tree (Fall)","diy":false,"buy":null,"sell":200,"colors":[],"variants":[[{"id":5728,"filename":"https://storage.googleapis.com/acdb/other/DIYPinecone.png","colors":[]}]],"recipe":null,"tag":"NA"},{"id":2867,"name":"pink cosmos","details":null,"source":"Picking flowers","diy":false,"buy":null,"sell":80,"colors":[],"variants":[[{"id":2867,"filename":"https://storage.googleapis.com/acdb/other/FlwCosmosPink.png","colors":[]}]],"recipe":null,"tag":"Plants"},{"id":3738,"name":"pink hyacinths","details":null,"source":"Picking flowers","diy":false,"buy":null,"sell":80,"colors":[],"variants":[[{"id":3738,"filename":"https://storage.googleapis.com/acdb/other/FlwHyacinthPink.png","colors":[]}]],"recipe":null,"tag":"Plants"},{"id":2991,"name":"pink lilies","details":null,"source":"Picking flowers","diy":false,"buy":null,"sell":80,"colors":[],"variants":[[{"id":2991,"filename":"https://storage.googleapis.com/acdb/other/FlwYuriPink.png","colors":[]}]],"recipe":null,"tag":"Plants"},{"id":3765,"name":"pink mums","details":null,"source":"Picking flowers","diy":false,"buy":null,"sell":80,"colors":[],"variants":[[{"id":3765,"filename":"https://storage.googleapis.com/acdb/other/FlwMumPink.png","colors":[]}]],"recipe":null,"tag":"Plants"},{"id":2943,"name":"pink roses","details":null,"source":"Picking flowers","diy":false,"buy":null,"sell":80,"colors":[],"variants":[[{"id":2943,"filename":"https://storage.googleapis.com/acdb/other/FlwRosePink.png","colors":[]}]],"recipe":null,"tag":"Plants"},{"id":2891,"name":"pink tulips","details":null,"source":"Picking flowers","diy":false,"buy":null,"sell":80,"colors":[],"variants":[[{"id":2891,"filename":"https://storage.googleapis.com/acdb/other/FlwTulipPink.png","colors":[]}]],"recipe":null,"tag":"Plants"},{"id":3720,"name":"pink windflowers","details":null,"source":"Picking flowers","diy":false,"buy":null,"sell":80,"colors":[],"variants":[[{"id":3720,"filename":"https://storage.googleapis.com/acdb/other/FlwAnemonesPink.png","colors":[]}]],"recipe":null,"tag":"Plants"},{"id":7684,"name":"pink wrapping paper","details":null,"source":"Nook's Cranny","diy":false,"buy":160,"sell":40,"colors":[],"variants":[[{"id":7684,"filename":"https://storage.googleapis.com/acdb/other/WPaperPink.png","colors":[]}]],"recipe":null,"tag":"NA"},{"id":3830,"name":"pink-cosmos plant","details":null,"source":"Red/white cosmos","diy":false,"buy":null,"sell":80,"colors":[],"variants":[[{"id":3830,"filename":"https://storage.googleapis.com/acdb/other/PltCosmosPink3.png","colors":[]}]],"recipe":null,"tag":"Plants"},{"id":3914,"name":"pink-hyacinth plant","details":null,"source":"Red/white hyacinths","diy":false,"buy":null,"sell":80,"colors":[],"variants":[[{"id":3914,"filename":"https://storage.googleapis.com/acdb/other/PltHyacinthPink3.png","colors":[]}]],"recipe":null,"tag":"Plants"},{"id":3892,"name":"pink-lily plant","details":null,"source":"Red/white lilies","diy":false,"buy":null,"sell":80,"colors":[],"variants":[[{"id":3892,"filename":"https://storage.googleapis.com/acdb/other/PltYuriPink3.png","colors":[]}]],"recipe":null,"tag":"Plants"},{"id":3930,"name":"pink-mum plant","details":null,"source":"Red/white mums","diy":false,"buy":null,"sell":80,"colors":[],"variants":[[{"id":3930,"filename":"https://storage.googleapis.com/acdb/other/PltMumPink3.png","colors":[]}]],"recipe":null,"tag":"Plants"},{"id":3868,"name":"pink-rose plant","details":null,"source":"Red/white roses","diy":false,"buy":null,"sell":80,"colors":[],"variants":[[{"id":3868,"filename":"https://storage.googleapis.com/acdb/other/PltRosePink3.png","colors":[]}]],"recipe":null,"tag":"Plants"},{"id":3842,"name":"pink-tulip plant","details":null,"source":"Red/white tulips","diy":false,"buy":null,"sell":80,"colors":[],"variants":[[{"id":3842,"filename":"https://storage.googleapis.com/acdb/other/PltTulipPink3.png","colors":[]}]],"recipe":null,"tag":"Plants"},{"id":3904,"name":"pink-windflower plant","details":null,"source":"Red/orange windflowers","diy":false,"buy":null,"sell":80,"colors":[],"variants":[[{"id":3904,"filename":"https://storage.googleapis.com/acdb/other/PltAnemonesPink3.png","colors":[]}]],"recipe":null,"tag":"Plants"},{"id":5987,"name":"Pisces fragment","details":null,"source":"Wishing on shooting stars (February 19 - March 20)","diy":false,"buy":null,"sell":500,"colors":[],"variants":[[{"id":5987,"filename":"https://storage.googleapis.com/acdb/other/StarpiecePisces.png","colors":[]}]],"recipe":null,"tag":"NA"},{"id":2578,"name":"pitfall seed","details":null,"source":"Crafting","diy":false,"buy":null,"sell":140,"colors":[],"variants":[[{"id":2578,"filename":"https://storage.googleapis.com/acdb/other/PitfallSeed.png","colors":[]}]],"recipe":null,"tag":"NA"},{"id":5827,"name":"plot 1 housing kit","details":null,"source":"Tom Nook","diy":false,"buy":null,"sell":null,"colors":[],"variants":[[{"id":5827,"filename":"https://storage.googleapis.com/acdb/other/HousingKitRcoQuestA.png","colors":[]}]],"recipe":null,"tag":"NA"},{"id":5828,"name":"plot 2 housing kit","details":null,"source":"Tom Nook","diy":false,"buy":null,"sell":null,"colors":[],"variants":[[{"id":5828,"filename":"https://storage.googleapis.com/acdb/other/HousingKitRcoQuestB.png","colors":[]}]],"recipe":null,"tag":"NA"},{"id":5829,"name":"plot 3 housing kit","details":null,"source":"Tom Nook","diy":false,"buy":null,"sell":null,"colors":[],"variants":[[{"id":5829,"filename":"https://storage.googleapis.com/acdb/other/HousingKitRcoQuestC.png","colors":[]}]],"recipe":null,"tag":"NA"},{"id":4480,"name":"present","details":null,"source":"Mail","diy":false,"buy":null,"sell":222,"colors":[],"variants":[[{"id":4480,"filename":"https://storage.googleapis.com/acdb/other/DummyPresentbox.png","colors":[]}]],"recipe":null,"tag":"Seasonal Decor"},{"id":7714,"name":"present (black)","details":null,"source":"Wrapping a present","diy":false,"buy":null,"sell":null,"colors":[],"variants":[[{"id":7714,"filename":"https://storage.googleapis.com/acdb/other/DummyWrappingBlack.png","colors":[]}]],"recipe":null,"tag":"NA"},{"id":7708,"name":"present (blue)","details":null,"source":"Wrapping a present","diy":false,"buy":null,"sell":null,"colors":[],"variants":[[{"id":7708,"filename":"https://storage.googleapis.com/acdb/other/DummyWrappingBlue.png","colors":[]}]],"recipe":null,"tag":"NA"},{"id":7712,"name":"present (brown)","details":null,"source":"Wrapping a present","diy":false,"buy":null,"sell":null,"colors":[],"variants":[[{"id":7712,"filename":"https://storage.googleapis.com/acdb/other/DummyWrappingBrown.png","colors":[]}]],"recipe":null,"tag":"NA"},{"id":7702,"name":"present (chartreuse)","details":null,"source":"Wrapping a present","diy":false,"buy":null,"sell":null,"colors":[],"variants":[[{"id":7702,"filename":"https://storage.googleapis.com/acdb/other/DummyWrappingLightGreen.png","colors":[]}]],"recipe":null,"tag":"NA"},{"id":7711,"name":"present (gold)","details":null,"source":"Wrapping a present","diy":false,"buy":null,"sell":null,"colors":[],"variants":[[{"id":7711,"filename":"https://storage.googleapis.com/acdb/other/DummyWrappingGold.png","colors":[]}]],"recipe":null,"tag":"NA"},{"id":7713,"name":"present (gray)","details":null,"source":"Wrapping a present","diy":false,"buy":null,"sell":null,"colors":[],"variants":[[{"id":7713,"filename":"https://storage.googleapis.com/acdb/other/DummyWrappingGary.png","colors":[]}]],"recipe":null,"tag":"NA"},{"id":7703,"name":"present (green)","details":null,"source":"Wrapping a present","diy":false,"buy":null,"sell":null,"colors":[],"variants":[[{"id":7703,"filename":"https://storage.googleapis.com/acdb/other/DummyWrappingGreen.png","colors":[]}]],"recipe":null,"tag":"NA"},{"id":7705,"name":"present (light-blue)","details":null,"source":"Wrapping a present","diy":false,"buy":null,"sell":null,"colors":[],"variants":[[{"id":7705,"filename":"https://storage.googleapis.com/acdb/other/DummyWrappingLightBlue.png","colors":[]}]],"recipe":null,"tag":"NA"},{"id":7704,"name":"present (mint)","details":null,"source":"Wrapping a present","diy":false,"buy":null,"sell":null,"colors":[],"variants":[[{"id":7704,"filename":"https://storage.googleapis.com/acdb/other/DummyWrappingMint.png","colors":[]}]],"recipe":null,"tag":"NA"},{"id":7707,"name":"present (navy)","details":null,"source":"Wrapping a present","diy":false,"buy":null,"sell":null,"colors":[],"variants":[[{"id":7707,"filename":"https://storage.googleapis.com/acdb/other/DummyWrappingNavy.png","colors":[]}]],"recipe":null,"tag":"NA"},{"id":7701,"name":"present (orange)","details":null,"source":"Wrapping a present","diy":false,"buy":null,"sell":null,"colors":[],"variants":[[{"id":7701,"filename":"https://storage.googleapis.com/acdb/other/DummyWrappingOrange.png","colors":[]}]],"recipe":null,"tag":"NA"},{"id":7700,"name":"present (pink)","details":null,"source":"Wrapping a present","diy":false,"buy":null,"sell":null,"colors":[],"variants":[[{"id":7700,"filename":"https://storage.googleapis.com/acdb/other/DummyWrappingPink.png","colors":[]}]],"recipe":null,"tag":"NA"},{"id":7706,"name":"present (purple)","details":null,"source":"Wrapping a present","diy":false,"buy":null,"sell":null,"colors":[],"variants":[[{"id":7706,"filename":"https://storage.googleapis.com/acdb/other/DummyWrappingPurple.png","colors":[]}]],"recipe":null,"tag":"NA"},{"id":7710,"name":"present (red)","details":null,"source":"Wrapping a present","diy":false,"buy":null,"sell":null,"colors":[],"variants":[[{"id":7710,"filename":"https://storage.googleapis.com/acdb/other/DummyWrappingRed.png","colors":[]}]],"recipe":null,"tag":"NA"},{"id":7709,"name":"present (white)","details":null,"source":"Wrapping a present","diy":false,"buy":null,"sell":null,"colors":[],"variants":[[{"id":7709,"filename":"https://storage.googleapis.com/acdb/other/DummyWrappingWhite.png","colors":[]}]],"recipe":null,"tag":"NA"},{"id":7699,"name":"present (yellow)","details":null,"source":"Wrapping a present","diy":false,"buy":null,"sell":null,"colors":[],"variants":[[{"id":7699,"filename":"https://storage.googleapis.com/acdb/other/DummyWrappingYellow.png","colors":[]}]],"recipe":null,"tag":"NA"},{"id":3751,"name":"purple hyacinths","details":null,"source":"Picking flowers","diy":false,"buy":null,"sell":240,"colors":[],"variants":[[{"id":3751,"filename":"https://storage.googleapis.com/acdb/other/FlwHyacinthPurple.png","colors":[]}]],"recipe":null,"tag":"Plants"},{"id":3762,"name":"purple mums","details":null,"source":"Picking flowers","diy":false,"buy":null,"sell":80,"colors":[],"variants":[[{"id":3762,"filename":"https://storage.googleapis.com/acdb/other/FlwMumPurple.png","colors":[]}]],"recipe":null,"tag":"Plants"},{"id":2923,"name":"purple pansies","details":null,"source":"Picking flowers","diy":false,"buy":null,"sell":240,"colors":[],"variants":[[{"id":2923,"filename":"https://storage.googleapis.com/acdb/other/FlwPansyPurple.png","colors":[]}]],"recipe":null,"tag":"Plants"},{"id":2951,"name":"purple roses","details":null,"source":"Picking flowers","diy":false,"buy":null,"sell":240,"colors":[],"variants":[[{"id":2951,"filename":"https://storage.googleapis.com/acdb/other/FlwRosePurple.png","colors":[]}]],"recipe":null,"tag":"Plants"},{"id":2899,"name":"purple tulips","details":null,"source":"Picking flowers","diy":false,"buy":null,"sell":240,"colors":[],"variants":[[{"id":2899,"filename":"https://storage.googleapis.com/acdb/other/FlwTulipPurple.png","colors":[]}]],"recipe":null,"tag":"Plants"},{"id":3727,"name":"purple windflowers","details":null,"source":"Picking flowers","diy":false,"buy":null,"sell":240,"colors":[],"variants":[[{"id":3727,"filename":"https://storage.googleapis.com/acdb/other/FlwAnemonesPurple.png","colors":[]}]],"recipe":null,"tag":"Plants"},{"id":7690,"name":"purple wrapping paper","details":null,"source":"Nook's Cranny","diy":false,"buy":160,"sell":40,"colors":[],"variants":[[{"id":7690,"filename":"https://storage.googleapis.com/acdb/other/WPaperPurple.png","colors":[]}]],"recipe":null,"tag":"NA"},{"id":3922,"name":"purple-hyacinth plant","details":null,"source":"Blue/blue hyacinths","diy":false,"buy":null,"sell":240,"colors":[],"variants":[[{"id":3922,"filename":"https://storage.googleapis.com/acdb/other/PltHyacinthPurple3.png","colors":[]}]],"recipe":null,"tag":"Plants"},{"id":3928,"name":"purple-mum plant","details":null,"source":"White/white mums","diy":false,"buy":null,"sell":80,"colors":[],"variants":[[{"id":3928,"filename":"https://storage.googleapis.com/acdb/other/PltMumPurple3.png","colors":[]}]],"recipe":null,"tag":"Plants"},{"id":3858,"name":"purple-pansy plant","details":null,"source":"Blue/blue pansies","diy":false,"buy":null,"sell":240,"colors":[],"variants":[[{"id":3858,"filename":"https://storage.googleapis.com/acdb/other/PltPansyPurple3.png","colors":[]}]],"recipe":null,"tag":"Plants"},{"id":3872,"name":"purple-rose plant","details":null,"source":"White/white roses","diy":false,"buy":null,"sell":240,"colors":[],"variants":[[{"id":3872,"filename":"https://storage.googleapis.com/acdb/other/PltRosePurple3.png","colors":[]}]],"recipe":null,"tag":"Plants"},{"id":3846,"name":"purple-tulip plant","details":null,"source":"Orange/orange tulips","diy":false,"buy":null,"sell":240,"colors":[],"variants":[[{"id":3846,"filename":"https://storage.googleapis.com/acdb/other/PltTulipPurple3.png","colors":[]}]],"recipe":null,"tag":"Plants"},{"id":3908,"name":"purple-windflower plant","details":null,"source":"Blue/blue windflowers\nBlue/pink windflowers","diy":false,"buy":null,"sell":240,"colors":[],"variants":[[{"id":3908,"filename":"https://storage.googleapis.com/acdb/other/PltAnemonesPurple3.png","colors":[]}]],"recipe":null,"tag":"Plants"},{"id":3280,"name":"rare mushroom","details":null,"source":"On ground (Mushroom Season)","diy":false,"buy":null,"sell":16000,"colors":[],"variants":[[{"id":3280,"filename":"https://storage.googleapis.com/acdb/other/MushRare.png","colors":[]}]],"recipe":null,"tag":"NA"},{"id":2304,"name":"red cosmos","details":null,"source":"Picking flowers","diy":false,"buy":null,"sell":40,"colors":[],"variants":[[{"id":2304,"filename":"https://storage.googleapis.com/acdb/other/FlwCosmosRed.png","colors":[]}]],"recipe":null,"tag":"Plants"},{"id":3744,"name":"red hyacinths","details":null,"source":"Picking flowers","diy":false,"buy":null,"sell":40,"colors":[],"variants":[[{"id":3744,"filename":"https://storage.googleapis.com/acdb/other/FlwHyacinthRed.png","colors":[]}]],"recipe":null,"tag":"Plants"},{"id":2983,"name":"red lilies","details":null,"source":"Picking flowers","diy":false,"buy":null,"sell":40,"colors":[],"variants":[[{"id":2983,"filename":"https://storage.googleapis.com/acdb/other/FlwYuriRed.png","colors":[]}]],"recipe":null,"tag":"Plants"},{"id":3768,"name":"red mums","details":null,"source":"Picking flowers","diy":false,"buy":null,"sell":40,"colors":[],"variants":[[{"id":3768,"filename":"https://storage.googleapis.com/acdb/other/FlwMumRed.png","colors":[]}]],"recipe":null,"tag":"Plants"},{"id":5730,"name":"red ornament","details":null,"source":"Shaking a cedar tree (Festive Season)","diy":false,"buy":null,"sell":50,"colors":[],"variants":[[{"id":5730,"filename":"https://storage.googleapis.com/acdb/other/DIYOrnamentRed.png","colors":[]}]],"recipe":null,"tag":"NA"},{"id":2911,"name":"red pansies","details":null,"source":"Picking flowers","diy":false,"buy":null,"sell":40,"colors":[],"variants":[[{"id":2911,"filename":"https://storage.googleapis.com/acdb/other/FlwPansyRed.png","colors":[]}]],"recipe":null,"tag":"Plants"},{"id":2935,"name":"red roses","details":null,"source":"Picking flowers","diy":false,"buy":null,"sell":40,"colors":[],"variants":[[{"id":2935,"filename":"https://storage.googleapis.com/acdb/other/FlwRoseRed.png","colors":[]}]],"recipe":null,"tag":"Plants"},{"id":2883,"name":"red tulips","details":null,"source":"Picking flowers","diy":false,"buy":null,"sell":40,"colors":[],"variants":[[{"id":2883,"filename":"https://storage.googleapis.com/acdb/other/FlwTulipRed.png","colors":[]}]],"recipe":null,"tag":"Plants"},{"id":3723,"name":"red windflowers","details":null,"source":"Picking flowers","diy":false,"buy":null,"sell":40,"colors":[],"variants":[[{"id":3723,"filename":"https://storage.googleapis.com/acdb/other/FlwAnemonesRed.png","colors":[]}]],"recipe":null,"tag":"Plants"},{"id":7694,"name":"red wrapping paper","details":null,"source":"Nook's Cranny","diy":false,"buy":160,"sell":40,"colors":[],"variants":[[{"id":7694,"filename":"https://storage.googleapis.com/acdb/other/WPaperRed.png","colors":[]}]],"recipe":null,"tag":"NA"},{"id":2626,"name":"red-cosmos bag","details":null,"source":"Nook's Cranny","diy":false,"buy":240,"sell":60,"colors":[],"variants":[[{"id":2626,"filename":"https://storage.googleapis.com/acdb/other/SeedCosmosRed.png","colors":[]}]],"recipe":null,"tag":"Plants"},{"id":3824,"name":"red-cosmos plant","details":null,"source":"Seed bag","diy":false,"buy":null,"sell":40,"colors":[],"variants":[[{"id":3824,"filename":"https://storage.googleapis.com/acdb/other/PltCosmosRed3.png","colors":[]}]],"recipe":null,"tag":"Plants"},{"id":3745,"name":"red-hyacinth bag","details":null,"source":"Nook's Cranny","diy":false,"buy":240,"sell":60,"colors":[],"variants":[[{"id":3745,"filename":"https://storage.googleapis.com/acdb/other/SeedHyacinthRed.png","colors":[]}]],"recipe":null,"tag":"Plants"},{"id":3918,"name":"red-hyacinth plant","details":null,"source":"Seed bag","diy":false,"buy":null,"sell":40,"colors":[],"variants":[[{"id":3918,"filename":"https://storage.googleapis.com/acdb/other/PltHyacinthRed3.png","colors":[]}]],"recipe":null,"tag":"Plants"},{"id":2984,"name":"red-lily bag","details":null,"source":"Nook's Cranny","diy":false,"buy":240,"sell":60,"colors":[],"variants":[[{"id":2984,"filename":"https://storage.googleapis.com/acdb/other/SeedYuriRed.png","colors":[]}]],"recipe":null,"tag":"Plants"},{"id":3888,"name":"red-lily plant","details":null,"source":"Seed bag","diy":false,"buy":null,"sell":40,"colors":[],"variants":[[{"id":3888,"filename":"https://storage.googleapis.com/acdb/other/PltYuriRed3.png","colors":[]}]],"recipe":null,"tag":"Plants"},{"id":3769,"name":"red-mum bag","details":null,"source":"Nook's Cranny","diy":false,"buy":240,"sell":60,"colors":[],"variants":[[{"id":3769,"filename":"https://storage.googleapis.com/acdb/other/SeedMumRed.png","colors":[]}]],"recipe":null,"tag":"Plants"},{"id":3932,"name":"red-mum plant","details":null,"source":"Seed bag","diy":false,"buy":null,"sell":40,"colors":[],"variants":[[{"id":3932,"filename":"https://storage.googleapis.com/acdb/other/PltMumRed3.png","colors":[]}]],"recipe":null,"tag":"Plants"},{"id":2912,"name":"red-pansy bag","details":null,"source":"Nook's Cranny","diy":false,"buy":240,"sell":60,"colors":[],"variants":[[{"id":2912,"filename":"https://storage.googleapis.com/acdb/other/SeedPansyRed.png","colors":[]}]],"recipe":null,"tag":"Plants"},{"id":3852,"name":"red-pansy plant","details":null,"source":"Seed bag","diy":false,"buy":null,"sell":40,"colors":[],"variants":[[{"id":3852,"filename":"https://storage.googleapis.com/acdb/other/PltPansyRed3.png","colors":[]}]],"recipe":null,"tag":"Plants"},{"id":2936,"name":"red-rose bag","details":null,"source":"Nook's Cranny","diy":false,"buy":240,"sell":60,"colors":[],"variants":[[{"id":2936,"filename":"https://storage.googleapis.com/acdb/other/SeedRoseRed.png","colors":[]}]],"recipe":null,"tag":"Plants"},{"id":3864,"name":"red-rose plant","details":null,"source":"Seed bag","diy":false,"buy":null,"sell":40,"colors":[],"variants":[[{"id":3864,"filename":"https://storage.googleapis.com/acdb/other/PltRoseRed3.png","colors":[]}]],"recipe":null,"tag":"Plants"},{"id":2884,"name":"red-tulip bag","details":null,"source":"Nook's Cranny","diy":false,"buy":240,"sell":60,"colors":[],"variants":[[{"id":2884,"filename":"https://storage.googleapis.com/acdb/other/SeedTulipRed.png","colors":[]}]],"recipe":null,"tag":"Plants"},{"id":3838,"name":"red-tulip plant","details":null,"source":"Seed bag","diy":false,"buy":null,"sell":40,"colors":[],"variants":[[{"id":3838,"filename":"https://storage.googleapis.com/acdb/other/PltTulipRed3.png","colors":[]}]],"recipe":null,"tag":"Plants"},{"id":3724,"name":"red-windflower bag","details":null,"source":"Nook's Cranny","diy":false,"buy":240,"sell":60,"colors":[],"variants":[[{"id":3724,"filename":"https://storage.googleapis.com/acdb/other/SeedAnemonesRed.png","colors":[]}]],"recipe":null,"tag":"Plants"},{"id":3906,"name":"red-windflower plant","details":null,"source":"Seed bag","diy":false,"buy":null,"sell":40,"colors":[],"variants":[[{"id":3906,"filename":"https://storage.googleapis.com/acdb/other/PltAnemonesRed3.png","colors":[]}]],"recipe":null,"tag":"Plants"},{"id":3277,"name":"round mushroom","details":null,"source":"On ground (Mushroom Season)","diy":false,"buy":null,"sell":200,"colors":[],"variants":[[{"id":3277,"filename":"https://storage.googleapis.com/acdb/other/MushRound.png","colors":[]}]],"recipe":null,"tag":"NA"},{"id":2389,"name":"rusted part","details":null,"source":"Recycle Box","diy":false,"buy":null,"sell":10,"colors":[],"variants":[[{"id":2389,"filename":"https://storage.googleapis.com/acdb/other/JohnnyQuestDust1.png","colors":[]}]],"recipe":null,"tag":"NA"},{"id":5996,"name":"Sagittarius fragment","details":null,"source":"Wishing on shooting stars (November 22 - December 21)","diy":false,"buy":null,"sell":500,"colors":[],"variants":[[{"id":5996,"filename":"https://storage.googleapis.com/acdb/other/StarpieceSagittarius.png","colors":[]}]],"recipe":null,"tag":"NA"},{"id":9261,"name":"Saharah Ticket","details":null,"source":"Saharah","diy":false,"buy":null,"sell":100,"colors":[],"variants":[[{"id":9261,"filename":"https://storage.googleapis.com/acdb/other/RollanTicket.png","colors":[]}]],"recipe":null,"tag":"NA"},{"id":1379,"name":"sand dollar","details":null,"source":"Beach","diy":false,"buy":null,"sell":120,"colors":[],"variants":[[{"id":1379,"filename":"https://storage.googleapis.com/acdb/other/ShellDriftSanddollar.png","colors":[]}]],"recipe":null,"tag":"NA"},{"id":2794,"name":"sapling","details":null,"source":"Nook's Cranny","diy":false,"buy":640,"sell":160,"colors":[],"variants":[[{"id":2794,"filename":"https://storage.googleapis.com/acdb/other/SeedOak.png","colors":[]}]],"recipe":null,"tag":"Plants"},{"id":5995,"name":"Scorpius fragment","details":null,"source":"Wishing on shooting stars (October 23 - November 21)","diy":false,"buy":null,"sell":500,"colors":[],"variants":[[{"id":5995,"filename":"https://storage.googleapis.com/acdb/other/StarpieceScorpio.png","colors":[]}]],"recipe":null,"tag":"NA"},{"id":1374,"name":"sea snail","details":null,"source":"Beach","diy":false,"buy":null,"sell":180,"colors":[],"variants":[[{"id":1374,"filename":"https://storage.googleapis.com/acdb/other/ShellDriftEbisu.png","colors":[]}]],"recipe":null,"tag":"NA"},{"id":2756,"name":"shop construction kit","details":null,"source":"Tom Nook","diy":false,"buy":null,"sell":null,"colors":[],"variants":[[{"id":2756,"filename":"https://storage.googleapis.com/acdb/other/ShopTent.png","colors":[]}]],"recipe":null,"tag":"NA"},{"id":5360,"name":"shop moving kit","details":null,"source":"Tom Nook","diy":false,"buy":null,"sell":null,"colors":[],"variants":[[{"id":5360,"filename":"https://storage.googleapis.com/acdb/other/MovingKitShop.png","colors":[]}]],"recipe":null,"tag":"NA"},{"id":3278,"name":"skinny mushroom","details":null,"source":"On ground (Mushroom Season)","diy":false,"buy":null,"sell":300,"colors":[],"variants":[[{"id":3278,"filename":"https://storage.googleapis.com/acdb/other/MushSlender.png","colors":[]}]],"recipe":null,"tag":"NA"},{"id":12513,"name":"sky egg","details":null,"source":"Colorful balloon (Bunny Day)","diy":false,"buy":null,"sell":200,"colors":[],"variants":[[{"id":12513,"filename":"https://storage.googleapis.com/acdb/other/EggSky.png","colors":[]}]],"recipe":null,"tag":"NA"},{"id":10309,"name":"Slingshot Recipe","details":null,"source":"Nook's Cranny","diy":false,"buy":300,"sell":200,"colors":[],"variants":[[{"id":10309,"filename":"https://storage.googleapis.com/acdb/other/DIYRecipeSlingShot.png","colors":[]}]],"recipe":null,"tag":"NA"},{"id":3539,"name":"snowflake","details":null,"source":"Catching with a net (Winter)","diy":false,"buy":null,"sell":200,"colors":[],"variants":[[{"id":3539,"filename":"https://storage.googleapis.com/acdb/other/SnowCrystal.png","colors":[]}]],"recipe":null,"tag":"NA"},{"id":2767,"name":"softwood","details":null,"source":"Chopping a tree","diy":false,"buy":null,"sell":60,"colors":[],"variants":[[{"id":2767,"filename":"https://storage.googleapis.com/acdb/other/DIYWoodSoft.png","colors":[]}]],"recipe":null,"tag":"NA"},{"id":2642,"name":"spoiled turnips","details":null,"source":"Expired turnips","diy":false,"buy":null,"sell":100,"colors":[],"variants":[[{"id":2642,"filename":"https://storage.googleapis.com/acdb/other/Kabu_Spoil.png","colors":[]}]],"recipe":null,"tag":"NA"},{"id":5983,"name":"star fragment","details":null,"source":"Wishing on shooting stars","diy":false,"buy":null,"sell":250,"colors":[],"variants":[[{"id":5983,"filename":"https://storage.googleapis.com/acdb/other/Starpiece.png","colors":[]}]],"recipe":null,"tag":"NA"},{"id":2502,"name":"stone","details":"X-Small shadow when fishing","source":"Hitting a rock, Fishing","diy":false,"buy":null,"sell":75,"colors":[],"variants":[[{"id":2502,"filename":"https://storage.googleapis.com/acdb/other/DIYStone.png","colors":[]}]],"recipe":null,"tag":"NA"},{"id":12510,"name":"stone egg","details":null,"source":"Hitting a rock (Bunny Day)","diy":false,"buy":null,"sell":200,"colors":[],"variants":[[{"id":12510,"filename":"https://storage.googleapis.com/acdb/other/EggRock.png","colors":[]}]],"recipe":null,"tag":"NA"},{"id":5982,"name":"summer shell","details":null,"source":"Beach (Summer)","diy":false,"buy":null,"sell":600,"colors":[],"variants":[[{"id":5982,"filename":"https://storage.googleapis.com/acdb/other/ShellDriftSummer.png","colors":[]}]],"recipe":null,"tag":"NA"},{"id":4411,"name":"tailors construction kit","details":null,"source":"Tom Nook","diy":false,"buy":null,"sell":null,"colors":[],"variants":[[{"id":4411,"filename":"https://storage.googleapis.com/acdb/other/HousingKitTailor.png","colors":[]}]],"recipe":null,"tag":"NA"},{"id":5359,"name":"tailors moving kit","details":null,"source":"Tom Nook","diy":false,"buy":null,"sell":null,"colors":[],"variants":[[{"id":5359,"filename":"https://storage.googleapis.com/acdb/other/MovingKitTailor.png","colors":[]}]],"recipe":null,"tag":"NA"},{"id":5932,"name":"tailors ticket","details":null,"source":"Label","diy":false,"buy":null,"sell":250,"colors":[],"variants":[[{"id":5932,"filename":"https://storage.googleapis.com/acdb/other/TailorTicket.png","colors":[]}]],"recipe":null,"tag":"NA"},{"id":5989,"name":"Taurus fragment","details":null,"source":"Wishing on shooting stars (April 20 - May 20)","diy":false,"buy":null,"sell":500,"colors":[],"variants":[[{"id":5989,"filename":"https://storage.googleapis.com/acdb/other/StarpieceTaurus.png","colors":[]}]],"recipe":null,"tag":"NA"},{"id":2750,"name":"tent","details":null,"source":"Tom Nook","diy":false,"buy":null,"sell":null,"colors":[],"variants":[[{"id":2750,"filename":"https://storage.googleapis.com/acdb/other/TutorialTent.png","colors":[]}]],"recipe":null,"tag":"NA"},{"id":5604,"name":"Test Your DIY Skills","details":null,"source":"Nook's Cranny","diy":false,"buy":2680,"sell":null,"colors":[],"variants":[[{"id":5604,"filename":"https://storage.googleapis.com/acdb/other/DIYbook2.png","colors":[]}]],"recipe":null,"tag":"NA"},{"id":2545,"name":"treasure","details":null,"source":"Digging up treasure for a villager's quest","diy":false,"buy":null,"sell":0,"colors":[],"variants":[[{"id":2545,"filename":"https://storage.googleapis.com/acdb/other/TreasureCapsule.png","colors":[]}]],"recipe":null,"tag":"NA"},{"id":2500,"name":"tree branch","details":null,"source":"Shaking a hardwood or cedar tree","diy":false,"buy":null,"sell":5,"colors":[],"variants":[[{"id":2500,"filename":"https://storage.googleapis.com/acdb/other/DIYBranch.png","colors":[]}]],"recipe":null,"tag":"NA"},{"id":7734,"name":"turnips","details":null,"source":"Daisy Mae (Sundays)","diy":false,"buy":null,"sell":0,"colors":[],"variants":[[{"id":7734,"filename":"https://storage.googleapis.com/acdb/other/PhotoStudioKabu.png","colors":[]}]],"recipe":null,"tag":"NA"},{"id":9046,"name":"Vaulting Pole Recipe","details":null,"source":"Nook's Cranny","diy":false,"buy":500,"sell":200,"colors":[],"variants":[[{"id":9046,"filename":"https://storage.googleapis.com/acdb/other/DIYRecipeLongWoodenStick.png","colors":[]}]],"recipe":null,"tag":"NA"},{"id":1375,"name":"venus comb","details":null,"source":"Beach","diy":false,"buy":null,"sell":300,"colors":[],"variants":[[{"id":1375,"filename":"https://storage.googleapis.com/acdb/other/ShellDriftHone.png","colors":[]}]],"recipe":null,"tag":"NA"},{"id":5993,"name":"Virgo fragment","details":null,"source":"Wishing on shooting stars (August 23 - September 22)","diy":false,"buy":null,"sell":500,"colors":[],"variants":[[{"id":5993,"filename":"https://storage.googleapis.com/acdb/other/StarpieceVirgo.png","colors":[]}]],"recipe":null,"tag":"NA"},{"id":3263,"name":"wasp nest","details":null,"source":"Shaking a hardwood or cedar tree","diy":false,"buy":null,"sell":300,"colors":[],"variants":[[{"id":3263,"filename":"https://storage.googleapis.com/acdb/other/Honeycomb.png","colors":[]}]],"recipe":null,"tag":"Ranch"},{"id":12514,"name":"water egg","details":null,"source":"Fishing (Bunny Day)","diy":false,"buy":null,"sell":200,"colors":[],"variants":[[{"id":12514,"filename":"https://storage.googleapis.com/acdb/other/EggFish.png","colors":[]}]],"recipe":null,"tag":"NA"},{"id":4642,"name":"What was this again?","details":null,"source":"Don't return lost item","diy":false,"buy":null,"sell":null,"colors":[],"variants":[[{"id":4642,"filename":"https://storage.googleapis.com/acdb/other/LostQuestBagDust.png","colors":[]},{"id":4643,"filename":"https://storage.googleapis.com/acdb/other/LostQuestBookDust.png","colors":[]},{"id":5427,"filename":"https://storage.googleapis.com/acdb/other/LostQuestNoteDust.png","colors":[]}]],"recipe":null,"tag":"NA"},{"id":4643,"name":"What was this again?","details":null,"source":"Don't return lost item","diy":false,"buy":null,"sell":null,"colors":[],"variants":[[{"id":4642,"filename":"https://storage.googleapis.com/acdb/other/LostQuestBagDust.png","colors":[]},{"id":4643,"filename":"https://storage.googleapis.com/acdb/other/LostQuestBookDust.png","colors":[]},{"id":5427,"filename":"https://storage.googleapis.com/acdb/other/LostQuestNoteDust.png","colors":[]}]],"recipe":null,"tag":"NA"},{"id":5427,"name":"What was this again?","details":null,"source":"Don't return lost item","diy":false,"buy":null,"sell":null,"colors":[],"variants":[[{"id":4642,"filename":"https://storage.googleapis.com/acdb/other/LostQuestBagDust.png","colors":[]},{"id":4643,"filename":"https://storage.googleapis.com/acdb/other/LostQuestBookDust.png","colors":[]},{"id":5427,"filename":"https://storage.googleapis.com/acdb/other/LostQuestNoteDust.png","colors":[]}]],"recipe":null,"tag":"NA"},{"id":2305,"name":"white cosmos","details":null,"source":"Picking flowers","diy":false,"buy":null,"sell":40,"colors":[],"variants":[[{"id":2305,"filename":"https://storage.googleapis.com/acdb/other/FlwCosmosWhite.png","colors":[]}]],"recipe":null,"tag":"Plants"},{"id":3730,"name":"white hyacinths","details":null,"source":"Picking flowers","diy":false,"buy":null,"sell":40,"colors":[],"variants":[[{"id":3730,"filename":"https://storage.googleapis.com/acdb/other/FlwHyacinthWhite.png","colors":[]}]],"recipe":null,"tag":"Plants"},{"id":2979,"name":"white lilies","details":null,"source":"Picking flowers","diy":false,"buy":null,"sell":40,"colors":[],"variants":[[{"id":2979,"filename":"https://storage.googleapis.com/acdb/other/FlwYuriWhite.png","colors":[]}]],"recipe":null,"tag":"Plants"},{"id":3754,"name":"white mums","details":null,"source":"Picking flowers","diy":false,"buy":null,"sell":40,"colors":[],"variants":[[{"id":3754,"filename":"https://storage.googleapis.com/acdb/other/FlwMumWhite.png","colors":[]}]],"recipe":null,"tag":"Plants"},{"id":2907,"name":"white pansies","details":null,"source":"Picking flowers","diy":false,"buy":null,"sell":40,"colors":[],"variants":[[{"id":2907,"filename":"https://storage.googleapis.com/acdb/other/FlwPansyWhite.png","colors":[]}]],"recipe":null,"tag":"Plants"},{"id":2931,"name":"white roses","details":null,"source":"Picking flowers","diy":false,"buy":null,"sell":40,"colors":[],"variants":[[{"id":2931,"filename":"https://storage.googleapis.com/acdb/other/FlwRoseWhite.png","colors":[]}]],"recipe":null,"tag":"Plants"},{"id":2879,"name":"white tulips","details":null,"source":"Picking flowers","diy":false,"buy":null,"sell":40,"colors":[],"variants":[[{"id":2879,"filename":"https://storage.googleapis.com/acdb/other/FlwTulipWhite.png","colors":[]}]],"recipe":null,"tag":"Plants"},{"id":3709,"name":"white windflowers","details":null,"source":"Picking flowers","diy":false,"buy":null,"sell":40,"colors":[],"variants":[[{"id":3709,"filename":"https://storage.googleapis.com/acdb/other/FlwAnemonesWhite.png","colors":[]}]],"recipe":null,"tag":"Plants"},{"id":7693,"name":"white wrapping paper","details":null,"source":"Nook's Cranny","diy":false,"buy":160,"sell":40,"colors":[],"variants":[[{"id":7693,"filename":"https://storage.googleapis.com/acdb/other/WPaperWhite.png","colors":[]}]],"recipe":null,"tag":"NA"},{"id":2629,"name":"white-cosmos bag","details":null,"source":"Nook's Cranny","diy":false,"buy":240,"sell":60,"colors":[],"variants":[[{"id":2629,"filename":"https://storage.googleapis.com/acdb/other/SeedCosmosWhite.png","colors":[]}]],"recipe":null,"tag":"Plants"},{"id":3826,"name":"white-cosmos plant","details":null,"source":"Seed bag","diy":false,"buy":null,"sell":40,"colors":[],"variants":[[{"id":3826,"filename":"https://storage.googleapis.com/acdb/other/PltCosmosWhite3.png","colors":[]}]],"recipe":null,"tag":"Plants"},{"id":3731,"name":"white-hyacinth bag","details":null,"source":"Nook's Cranny","diy":false,"buy":240,"sell":60,"colors":[],"variants":[[{"id":3731,"filename":"https://storage.googleapis.com/acdb/other/SeedHyacinthWhite.png","colors":[]}]],"recipe":null,"tag":"Plants"},{"id":3910,"name":"white-hyacinth plant","details":null,"source":"Seed bag","diy":false,"buy":null,"sell":40,"colors":[],"variants":[[{"id":3910,"filename":"https://storage.googleapis.com/acdb/other/PltHyacinthWhite3.png","colors":[]}]],"recipe":null,"tag":"Plants"},{"id":2980,"name":"white-lily bag","details":null,"source":"Nook's Cranny","diy":false,"buy":240,"sell":60,"colors":[],"variants":[[{"id":2980,"filename":"https://storage.googleapis.com/acdb/other/SeedYuriWhite.png","colors":[]}]],"recipe":null,"tag":"Plants"},{"id":3886,"name":"white-lily plant","details":null,"source":"Seed bag","diy":false,"buy":null,"sell":40,"colors":[],"variants":[[{"id":3886,"filename":"https://storage.googleapis.com/acdb/other/PltYuriWhite3.png","colors":[]}]],"recipe":null,"tag":"Plants"},{"id":3755,"name":"white-mum bag","details":null,"source":"Nook's Cranny","diy":false,"buy":240,"sell":60,"colors":[],"variants":[[{"id":3755,"filename":"https://storage.googleapis.com/acdb/other/SeedMumWhite.png","colors":[]}]],"recipe":null,"tag":"Plants"},{"id":3924,"name":"white-mum plant","details":null,"source":"Seed bag","diy":false,"buy":null,"sell":40,"colors":[],"variants":[[{"id":3924,"filename":"https://storage.googleapis.com/acdb/other/PltMumWhite3.png","colors":[]}]],"recipe":null,"tag":"Plants"},{"id":2908,"name":"white-pansy bag","details":null,"source":"Nook's Cranny","diy":false,"buy":240,"sell":60,"colors":[],"variants":[[{"id":2908,"filename":"https://storage.googleapis.com/acdb/other/SeedPansyWhite.png","colors":[]}]],"recipe":null,"tag":"Plants"},{"id":3850,"name":"white-pansy plant","details":null,"source":"Seed bag","diy":false,"buy":null,"sell":40,"colors":[],"variants":[[{"id":3850,"filename":"https://storage.googleapis.com/acdb/other/PltPansyWhite3.png","colors":[]}]],"recipe":null,"tag":"Plants"},{"id":2932,"name":"white-rose bag","details":null,"source":"Nook's Cranny","diy":false,"buy":240,"sell":60,"colors":[],"variants":[[{"id":2932,"filename":"https://storage.googleapis.com/acdb/other/SeedRoseWhite.png","colors":[]}]],"recipe":null,"tag":"Plants"},{"id":3862,"name":"white-rose plant","details":null,"source":"Seed bag","diy":false,"buy":null,"sell":40,"colors":[],"variants":[[{"id":3862,"filename":"https://storage.googleapis.com/acdb/other/PltRoseWhite3.png","colors":[]}]],"recipe":null,"tag":"Plants"},{"id":2880,"name":"white-tulip bag","details":null,"source":"Nook's Cranny","diy":false,"buy":240,"sell":60,"colors":[],"variants":[[{"id":2880,"filename":"https://storage.googleapis.com/acdb/other/SeedTulipWhite.png","colors":[]}]],"recipe":null,"tag":"Plants"},{"id":3836,"name":"white-tulip plant","details":null,"source":"Seed bag","diy":false,"buy":null,"sell":40,"colors":[],"variants":[[{"id":3836,"filename":"https://storage.googleapis.com/acdb/other/PltTulipWhite3.png","colors":[]}]],"recipe":null,"tag":"Plants"},{"id":3710,"name":"white-windflower bag","details":null,"source":"Nook's Cranny","diy":false,"buy":240,"sell":60,"colors":[],"variants":[[{"id":3710,"filename":"https://storage.googleapis.com/acdb/other/SeedAnemonesWhite.png","colors":[]}]],"recipe":null,"tag":"Plants"},{"id":3898,"name":"white-windflower plant","details":null,"source":"Seed bag","diy":false,"buy":null,"sell":40,"colors":[],"variants":[[{"id":3898,"filename":"https://storage.googleapis.com/acdb/other/PltAnemonesWhite3.png","colors":[]}]],"recipe":null,"tag":"Plants"},{"id":5605,"name":"Wildest Dreams DIY","details":null,"source":"Nook's Cranny","diy":false,"buy":6980,"sell":null,"colors":[],"variants":[[{"id":5605,"filename":"https://storage.googleapis.com/acdb/other/DIYbook3.png","colors":[]}]],"recipe":null,"tag":"NA"},{"id":4702,"name":"Wisp spirit piece","details":null,"source":"Catching with a net while on a quest for Wisp","diy":false,"buy":null,"sell":null,"colors":[],"variants":[[{"id":4702,"filename":"https://storage.googleapis.com/acdb/other/YutaroWisp.png","colors":[]}]],"recipe":null,"tag":"NA"},{"id":2768,"name":"wood","details":null,"source":"Chopping a tree","diy":false,"buy":null,"sell":60,"colors":[],"variants":[[{"id":2768,"filename":"https://storage.googleapis.com/acdb/other/DIYWoodNormal.png","colors":[]}]],"recipe":null,"tag":"NA"},{"id":12512,"name":"wood egg","details":null,"source":"Chopping a tree (Bunny Day)","diy":false,"buy":null,"sell":200,"colors":[],"variants":[[{"id":12512,"filename":"https://storage.googleapis.com/acdb/other/EggForest.png","colors":[]}]],"recipe":null,"tag":"NA"},{"id":2863,"name":"yellow cosmos","details":null,"source":"Picking flowers","diy":false,"buy":null,"sell":40,"colors":[],"variants":[[{"id":2863,"filename":"https://storage.googleapis.com/acdb/other/FlwCosmosYellow.png","colors":[]}]],"recipe":null,"tag":"Plants"},{"id":3734,"name":"yellow hyacinths","details":null,"source":"Picking flowers","diy":false,"buy":null,"sell":40,"colors":[],"variants":[[{"id":3734,"filename":"https://storage.googleapis.com/acdb/other/FlwHyacinthYellow.png","colors":[]}]],"recipe":null,"tag":"Plants"},{"id":2987,"name":"yellow lilies","details":null,"source":"Picking flowers","diy":false,"buy":null,"sell":40,"colors":[],"variants":[[{"id":2987,"filename":"https://storage.googleapis.com/acdb/other/FlwYuriYellow.png","colors":[]}]],"recipe":null,"tag":"Plants"},{"id":3758,"name":"yellow mums","details":null,"source":"Picking flowers","diy":false,"buy":null,"sell":40,"colors":[],"variants":[[{"id":3758,"filename":"https://storage.googleapis.com/acdb/other/FlwMumYellow.png","colors":[]}]],"recipe":null,"tag":"Plants"},{"id":2915,"name":"yellow pansies","details":null,"source":"Picking flowers","diy":false,"buy":null,"sell":40,"colors":[],"variants":[[{"id":2915,"filename":"https://storage.googleapis.com/acdb/other/FlwPansyYellow.png","colors":[]}]],"recipe":null,"tag":"Plants"},{"id":2939,"name":"yellow roses","details":null,"source":"Picking flowers","diy":false,"buy":null,"sell":40,"colors":[],"variants":[[{"id":2939,"filename":"https://storage.googleapis.com/acdb/other/FlwRoseYellow.png","colors":[]}]],"recipe":null,"tag":"Plants"},{"id":2887,"name":"yellow tulips","details":null,"source":"Picking flowers","diy":false,"buy":null,"sell":40,"colors":[],"variants":[[{"id":2887,"filename":"https://storage.googleapis.com/acdb/other/FlwTulipYellow.png","colors":[]}]],"recipe":null,"tag":"Plants"},{"id":7683,"name":"yellow wrapping paper","details":null,"source":"Nook's Cranny","diy":false,"buy":160,"sell":40,"colors":[],"variants":[[{"id":7683,"filename":"https://storage.googleapis.com/acdb/other/WPaperYellow.png","colors":[]}]],"recipe":null,"tag":"NA"},{"id":2864,"name":"yellow-cosmos bag","details":null,"source":"Nook's Cranny","diy":false,"buy":240,"sell":60,"colors":[],"variants":[[{"id":2864,"filename":"https://storage.googleapis.com/acdb/other/SeedCosmosYellow.png","colors":[]}]],"recipe":null,"tag":"Plants"},{"id":3828,"name":"yellow-cosmos plant","details":null,"source":"Seed bag","diy":false,"buy":null,"sell":40,"colors":[],"variants":[[{"id":3828,"filename":"https://storage.googleapis.com/acdb/other/PltCosmosYellow3.png","colors":[]}]],"recipe":null,"tag":"Plants"},{"id":3735,"name":"yellow-hyacinth bag","details":null,"source":"Nook's Cranny","diy":false,"buy":240,"sell":60,"colors":[],"variants":[[{"id":3735,"filename":"https://storage.googleapis.com/acdb/other/SeedHyacinthYellow.png","colors":[]}]],"recipe":null,"tag":"Plants"},{"id":3912,"name":"yellow-hyacinth plant","details":null,"source":"Seed bag","diy":false,"buy":null,"sell":40,"colors":[],"variants":[[{"id":3912,"filename":"https://storage.googleapis.com/acdb/other/PltHyacinthYellow3.png","colors":[]}]],"recipe":null,"tag":"Plants"},{"id":2988,"name":"yellow-lily bag","details":null,"source":"Nook's Cranny","diy":false,"buy":240,"sell":60,"colors":[],"variants":[[{"id":2988,"filename":"https://storage.googleapis.com/acdb/other/SeedYuriYellow.png","colors":[]}]],"recipe":null,"tag":"Plants"},{"id":3890,"name":"yellow-lily plant","details":null,"source":"Seed bag","diy":false,"buy":null,"sell":40,"colors":[],"variants":[[{"id":3890,"filename":"https://storage.googleapis.com/acdb/other/PltYuriYellow3.png","colors":[]}]],"recipe":null,"tag":"Plants"},{"id":3759,"name":"yellow-mum bag","details":null,"source":"Nook's Cranny","diy":false,"buy":240,"sell":60,"colors":[],"variants":[[{"id":3759,"filename":"https://storage.googleapis.com/acdb/other/SeedMumYellow.png","colors":[]}]],"recipe":null,"tag":"Plants"},{"id":3926,"name":"yellow-mum plant","details":null,"source":"Seed bag","diy":false,"buy":null,"sell":40,"colors":[],"variants":[[{"id":3926,"filename":"https://storage.googleapis.com/acdb/other/PltMumYellow3.png","colors":[]}]],"recipe":null,"tag":"Plants"},{"id":2916,"name":"yellow-pansy bag","details":null,"source":"Nook's Cranny","diy":false,"buy":240,"sell":60,"colors":[],"variants":[[{"id":2916,"filename":"https://storage.googleapis.com/acdb/other/SeedPansyYellow.png","colors":[]}]],"recipe":null,"tag":"Plants"},{"id":3854,"name":"yellow-pansy plant","details":null,"source":"Seed bag","diy":false,"buy":null,"sell":40,"colors":[],"variants":[[{"id":3854,"filename":"https://storage.googleapis.com/acdb/other/PltPansyYellow3.png","colors":[]}]],"recipe":null,"tag":"Plants"},{"id":2940,"name":"yellow-rose bag","details":null,"source":"Nook's Cranny","diy":false,"buy":240,"sell":60,"colors":[],"variants":[[{"id":2940,"filename":"https://storage.googleapis.com/acdb/other/SeedRoseYellow.png","colors":[]}]],"recipe":null,"tag":"Plants"},{"id":3866,"name":"yellow-rose plant","details":null,"source":"Seed bag","diy":false,"buy":null,"sell":40,"colors":[],"variants":[[{"id":3866,"filename":"https://storage.googleapis.com/acdb/other/PltRoseYellow3.png","colors":[]}]],"recipe":null,"tag":"Plants"},{"id":2888,"name":"yellow-tulip bag","details":null,"source":"Nook's Cranny","diy":false,"buy":240,"sell":60,"colors":[],"variants":[[{"id":2888,"filename":"https://storage.googleapis.com/acdb/other/SeedTulipYellow.png","colors":[]}]],"recipe":null,"tag":"Plants"},{"id":3840,"name":"yellow-tulip plant","details":null,"source":"Seed bag","diy":false,"buy":null,"sell":40,"colors":[],"variants":[[{"id":3840,"filename":"https://storage.googleapis.com/acdb/other/PltTulipYellow3.png","colors":[]}]],"recipe":null,"tag":"Plants"},{"id":5729,"name":"young spring bamboo","details":null,"source":"Chopping a bamboo tree (Spring)","diy":false,"buy":null,"sell":200,"colors":[],"variants":[[{"id":5729,"filename":"https://storage.googleapis.com/acdb/other/DIYBambooSpring.png","colors":[]}]],"recipe":null,"tag":"NA"}]